CONTRIBUTE.md
LICENSE.txt
MANIFEST.in
README.rst
brocadetool.conf.example
requirements.txt
setup.py
brocade_tool.egg-info/PKG-INFO
brocade_tool.egg-info/SOURCES.txt
brocade_tool.egg-info/dependency_links.txt
brocade_tool.egg-info/entry_points.txt
brocade_tool.egg-info/requires.txt
brocade_tool.egg-info/top_level.txt
brocadetool/__init__.py
brocadetool/brocade_exceptions.py
brocadetool/brocadetool.py
brocadetool/snmp.py
brocadetool/utils.py